eunomia/__init__.py
eunomia/agents.py
eunomia/eunomia.py
eunomia/general.py
eunomia/parser.py
eunomia/prompts.py
eunomia/tools.py
eunomia/tools_list.py
eunomia/docs_utils/__init__.py
eunomia/docs_utils/docs.py
materials_eunomia-1.1.0.dist-info/LICENSE
materials_eunomia-1.1.0.dist-info/METADATA
materials_eunomia-1.1.0.dist-info/WHEEL
materials_eunomia-1.1.0.dist-info/top_level.txt
materials_eunomia-1.1.0.dist-info/RECORD
