Metadata-Version: 2.1
Name: materials-eunomia
Version: 1.1.0
Summary: Chemist AI Agent for Developing Materials Datasets with Natural Language Prompts
Home-page: https://github.com/AI4ChemS/Eunomia
Author: Mehrad Ansari
Author-email: mehrad.ans@gmail.com
License: MIT license
Keywords: eunomia
Classifier: Development Status :: 2 - Pre-Alpha
Classifier: Intended Audience :: Developers
Classifier: License :: OSI Approved :: MIT License
Classifier: Natural Language :: English
Classifier: Programming Language :: Python :: 3.7
Classifier: Programming Language :: Python :: 3.8
Classifier: Programming Language :: Python :: 3.9
Requires-Python: >=3.6
License-File: LICENSE
Requires-Dist: black ==21.7b0
Requires-Dist: pydantic ==2.9.2
Requires-Dist: openai ==1.23.6
Requires-Dist: langchain-openai ==0.1.4
Requires-Dist: langchain-community ==0.0.34
Requires-Dist: llama-index-core ==0.10.68
Requires-Dist: openapi-schema-pydantic ==1.2.4
Requires-Dist: faiss-cpu ==1.7.4
Requires-Dist: langchain ==0.1.16
Requires-Dist: pypdf
Requires-Dist: tiktoken
Requires-Dist: matplotlib
Requires-Dist: seaborn
Requires-Dist: pandas
Requires-Dist: fuzzywuzzy
Requires-Dist: PyYAML
Requires-Dist: llama-index ==0.10.31
Requires-Dist: unstructured
Requires-Dist: markdown
Requires-Dist: python-Levenshtein
